<annotation>
	<folder>Data</folder>
	<filename>resized189.png</filename>
	<path>/home/alice/stage/Data/resized189.png</path>
	<source>
		<database>Unknown</database>
	</source>
	<size>
		<width>640</width>
		<height>311</height>
		<depth>3</depth>
	</size>
	<segmented>0</segmented>
	<object>
		<name>Rock</name>
		<pose>Unspecified</pose>
		<truncated>0</truncated>
		<difficult>0</difficult>
		<bndbox>
			<xmin>187</xmin>
			<ymin>46</ymin>
			<xmax>441</xmax>
			<ymax>234</ymax>
		</bndbox>
	</object>
</annotation>
